numpy_choices/LICENSE
numpy_choices/README.MD
numpy_choices/__init__.py
numpy_choices/requirements.txt
numpy_choices/thirdparty.json
numpy_choices-0.10.dist-info/LICENSE.rst
numpy_choices-0.10.dist-info/METADATA
numpy_choices-0.10.dist-info/WHEEL
numpy_choices-0.10.dist-info/top_level.txt
numpy_choices-0.10.dist-info/RECORD
